integral_site_config/__init__.py
integral_site_config/cli.py
integral_site_config-0.1.0.dist-info/AUTHORS.rst
integral_site_config-0.1.0.dist-info/LICENSE
integral_site_config-0.1.0.dist-info/METADATA
integral_site_config-0.1.0.dist-info/WHEEL
integral_site_config-0.1.0.dist-info/entry_points.txt
integral_site_config-0.1.0.dist-info/top_level.txt
integral_site_config-0.1.0.dist-info/RECORD
