Metadata-Version: 2.1
Name: integral-site-config
Version: 0.1.0
Summary: Configuration for INTEGRAL site
Home-page: https://github.com/volodymyrss/integral_site_config
Author: Volodymyr Savchenko
Author-email: contact@volodymyrsavchenko.com
License: MIT license
Keywords: integral_site_config
Platform: UNKNOWN
Classifier: Development Status :: 2 - Pre-Alpha
Classifier: Intended Audience :: Developers
Classifier: License :: OSI Approved :: MIT License
Classifier: Natural Language :: English
Classifier: Programming Language :: Python :: 3
Classifier: Programming Language :: Python :: 3.6
Classifier: Programming Language :: Python :: 3.7
Classifier: Programming Language :: Python :: 3.8
Requires-Python: >=3.6
Requires-Dist: Click (>=7.0)
